tempr2/__init__.py
tempr2/py.typed
tempr2-0.1.0.dist-info/METADATA
tempr2-0.1.0.dist-info/WHEEL
tempr2-0.1.0.dist-info/RECORD
